README.md
setup.py
apitoolbox/__init__.py
apitoolbox/auth.py
apitoolbox/crud.py
apitoolbox/db_registry.py
apitoolbox/middleware.py
apitoolbox/types.py
apitoolbox/tz.py
apitoolbox/utils.py
apitoolbox.egg-info/PKG-INFO
apitoolbox.egg-info/SOURCES.txt
apitoolbox.egg-info/dependency_links.txt
apitoolbox.egg-info/requires.txt
apitoolbox.egg-info/top_level.txt
apitoolbox/endpoints/__init__.py
apitoolbox/endpoints/assets.py
apitoolbox/endpoints/base.py
apitoolbox/endpoints/confirm.py
apitoolbox/endpoints/groups.py
apitoolbox/endpoints/login.py
apitoolbox/endpoints/logout.py
apitoolbox/endpoints/permissions.py
apitoolbox/endpoints/register.py
apitoolbox/endpoints/users.py
apitoolbox/models/__init__.py
apitoolbox/models/associations.py
apitoolbox/models/base.py
apitoolbox/models/events.py
apitoolbox/models/groups.py
apitoolbox/models/mixins.py
apitoolbox/models/permissions.py
apitoolbox/models/types.py
apitoolbox/models/users.py
tests/data/__init__.py
tests/data/models.py
tests/data/people.py
tests/endpoints/__init__.py
tests/endpoints/test_assets.py
tests/endpoints/test_base.py
tests/endpoints/test_confirm.py
tests/endpoints/test_groups.py
tests/endpoints/test_login.py
tests/endpoints/test_logout.py
tests/endpoints/test_register.py
tests/endpoints/test_users.py
tests/models/__init__.py
tests/models/test_events.py
tests/models/test_mixins.py
tests/models/test_models.py
tests/models/test_types.py