Metadata-Version: 2.1
Name: apitoolbox
Version: 0.12.0
Summary: Full-stack async framework for Python.
Home-page: https://github.com/zuarbase/apitoolbox
Author: Matthew Laue
Author-email: matt@zuar.com
License: UNKNOWN
Download-URL: https://github.com/zuarbase/apitoolbox/archive/v0.12.0.tar.gz
Platform: UNKNOWN
Provides-Extra: dev
Provides-Extra: prod
